cmdgpt/__init__.py
cmdgpt/functions.py
cmdgpt/main.py
cmdgpt/openai_func.py
cmdgpt/presets.py
cmdgpt/utils.py
cmdgpt-0.4.1.dist-info/LICENSE
cmdgpt-0.4.1.dist-info/METADATA
cmdgpt-0.4.1.dist-info/WHEEL
cmdgpt-0.4.1.dist-info/entry_points.txt
cmdgpt-0.4.1.dist-info/top_level.txt
cmdgpt-0.4.1.dist-info/RECORD
