Metadata-Version: 2.1
Name: cmdgpt
Version: 0.4.1
Summary: Interact with the command line using natural language | 用自然语言操控命令行
Home-page: https://github.com/MZhao-ouo/CMDGPT
Author: MZhao
Author-email: mzhao.ouo@gmail.com
License: MIT
License-File: LICENSE
Requires-Dist: requests
Requires-Dist: colorama
